LICENSE
MANIFEST.in
README.md
setup.cfg
setup.py
nanoservice/__init__.py
nanoservice/client.py
nanoservice/config.py
nanoservice/crypto.py
nanoservice/encoder.py
nanoservice/error.py
nanoservice/pubsub.py
nanoservice/service.py
nanoservice.egg-info/PKG-INFO
nanoservice.egg-info/SOURCES.txt
nanoservice.egg-info/dependency_links.txt
nanoservice.egg-info/requires.txt
nanoservice.egg-info/top_level.txt
test/test_base_client.py
test/test_base_service.py
test/test_config.py
test/test_crypto.py
test/test_encoders.py
test/test_pub_sub.py
test/test_req_rep.py