Metadata-Version: 1.1
Name: nanoservice
Version: 0.5.3
Summary: nanoservice is a small Python library for writing lightweight networked services using nanomsg
Home-page: https://github.com/walkr/nanoservice
Author: Tony Walker
Author-email: walkr.walkr@gmail.com
License: MIT
Platform: UNKNOWN
Classifier: License :: OSI Approved :: MIT License
Classifier: Programming Language :: Python :: 2.7
Classifier: Programming Language :: Python :: 3
Classifier: Programming Language :: Python :: 3.3
Classifier: Programming Language :: Python :: 3.4
Classifier: Programming Language :: Python :: Implementation :: CPython
Classifier: Programming Language :: Python :: Implementation :: PyPy
